muji/__init__.py
muji/interpreter.py
muji/lexer.py
muji/main.py
muji/parser.py
muji/token_types.py
muji_lang-1.0.0.dist-info/METADATA
muji_lang-1.0.0.dist-info/WHEEL
muji_lang-1.0.0.dist-info/entry_points.txt
muji_lang-1.0.0.dist-info/top_level.txt
muji_lang-1.0.0.dist-info/RECORD
