Metadata-Version: 2.1
Name: muji-lang
Version: 1.0.0
Summary: Muji Programming Language Interpreter
Home-page: https://github.com/theSandeshStha/muji-bhasa
Author: Your Name
Author-email: guluguluman4@gmail.com
Classifier: Programming Language :: Python :: 3
Classifier: Operating System :: OS Independent
Requires-Python: >=3.6
